create_agent_skills_repo/__init__.py
create_agent_skill_repo-0.1.1.dist-info/METADATA
create_agent_skill_repo-0.1.1.dist-info/WHEEL
create_agent_skill_repo-0.1.1.dist-info/entry_points.txt
create_agent_skill_repo-0.1.1.dist-info/RECORD
