Metadata-Version: 2.4
Name: create-agent-skill-repo
Version: 0.1.1
Summary: Create a personal agent-skills repository for Claude Code, Codex, OpenCode, Amp, Clawdbot and others.
License-Expression: MIT
Requires-Python: >=3.10
Requires-Dist: agent-skills-upd>=0.1.1
